MANIFEST.in
README.rst
setup.py
happy_blog/__init__.py
happy_blog/admin.py
happy_blog/cms_app.py
happy_blog/cms_plugins.py
happy_blog/models.py
happy_blog/urls.py
happy_blog/views.py
happy_blog.egg-info/PKG-INFO
happy_blog.egg-info/SOURCES.txt
happy_blog.egg-info/dependency_links.txt
happy_blog.egg-info/not-zip-safe
happy_blog.egg-info/requires.txt
happy_blog.egg-info/top_level.txt
happy_blog/migrations/0001_initial.py
happy_blog/migrations/__init__.py
happy_blog/templates/happy_blog/archive.html
happy_blog/templates/happy_blog/entry_detail.html
happy_blog/templates/happy_blog/feed_item_description.html
happy_blog/templates/happy_blog/feed_item_title.html
happy_blog/templates/happy_blog/latest.html
happy_blog/templates/happy_blog/latest_list.html