Metadata-Version: 1.0
Name: happy-blog
Version: 0.2.2
Summary: A simple django blog app that uses django-hvad for translations.
Home-page: https://github.com/neo64bit/happy-blog
Author: Ales Kocjancic
Author-email: ales.kocjancic@divio.ch
License: UNKNOWN
Platform: UNKNOWN
Classifier: Development Status :: 3 - Alpha
Classifier: Framework :: Django
Classifier: Intended Audience :: Developers
Classifier: License :: OSI Approved :: BSD License
Classifier: Operating System :: OS Independent
Classifier: Programming Language :: Python :: 2.5
Classifier: Programming Language :: Python :: 2.6
Classifier: Programming Language :: Python :: 2.7
Classifier: Topic :: Internet :: WWW/HTTP :: Dynamic Content
